djangosetupheist/__init__.py
djangosetupheist/cli.py
djangosetupheist/config.py
djangosetupheist/methods.py
djangosetupheist/utils.py
djangosetupheist/__pycache__/__init__.cpython-312.pyc
djangosetupheist/__pycache__/cli.cpython-312.pyc
djangosetupheist/__pycache__/methods.cpython-312.pyc
djangosetupheist/__pycache__/utils.cpython-312.pyc
djangosetupheist/assets/.envtemp
djangosetupheist/assets/app_urls.py
djangosetupheist/assets/apps.py
djangosetupheist/assets/appsConfig.py
djangosetupheist/assets/settings.py
djangosetupheist/assets/urls.py
djangosetupheist-0.6.2.dist-info/LICENSE
djangosetupheist-0.6.2.dist-info/METADATA
djangosetupheist-0.6.2.dist-info/WHEEL
djangosetupheist-0.6.2.dist-info/entry_points.txt
djangosetupheist-0.6.2.dist-info/top_level.txt
djangosetupheist-0.6.2.dist-info/RECORD
