Metadata-Version: 2.2
Name: djangosetupheist
Version: 0.6.2
Summary: A Django project setup automation tool
Home-page: https://github.com/eliHeist/django_setup.git
Author: eliHeist
Classifier: Programming Language :: Python :: 3
Classifier: License :: OSI Approved :: GNU General Public License v3 (GPLv3)
Classifier: Operating System :: OS Independent
Requires-Python: >=3.5
License-File: LICENSE
Requires-Dist: django
Requires-Dist: django-environ
Dynamic: author
Dynamic: classifier
Dynamic: description
Dynamic: description-content-type
Dynamic: home-page
Dynamic: requires-dist
Dynamic: requires-python
Dynamic: summary
